mi_pyral-2.8.4.dist-info/licenses/LICENSE
pyral/__init__.py
pyral/__main__.py
pyral/database.py
pyral/exceptions.py
pyral/log.conf
pyral/print_table.py
pyral/relation.py
pyral/relvar.py
pyral/rtypes.py
pyral/transaction.py
pyral/experiments/__init__.py
pyral/experiments/bool_play.py
pyral/experiments/dogs_example.py
pyral/experiments/join_play.py
pyral/experiments/restrict_play.py
pyral/experiments/restrict_play_ac.py
pyral/experiments/rv_play.py
pyral/experiments/setops_play.py
pyral/experiments/sum_play.py
pyral/experiments/sum_play2.py
pyral/experiments/union_play.py
pyral/tcl_scripts/init_TclRAL.tcl
pyral/tcl_scripts/MacIntel/ral-0.12.2.tm
pyral/tcl_scripts/MacIntel/ralutil-0.12.2.tm
pyral/tcl_scripts/MacSilicon/ral-0.12.2.tm
pyral/tcl_scripts/MacSilicon/ralutil-0.12.2.tm
mi_pyral-2.8.4.dist-info/METADATA
mi_pyral-2.8.4.dist-info/WHEEL
mi_pyral-2.8.4.dist-info/entry_points.txt
mi_pyral-2.8.4.dist-info/top_level.txt
mi_pyral-2.8.4.dist-info/RECORD
