Metadata-Version: 2.4
Name: mi-pyral
Version: 2.8.4
Summary: PyRAL Pythonic interface to TclRAL
Author-email: Leon Starr <leon_starr@modelint.com>
License: MIT License
Project-URL: repository, https://github.com/modelint/PyRAL
Project-URL: documentation, https://github.com/modelint/PyRAL/wiki
Keywords: relational,tcl,database,cjdate,darwen,tutoriald,thirdmanifesto
Classifier: License :: OSI Approved :: MIT License
Classifier: Programming Language :: Python
Classifier: Programming Language :: Python :: 3
Requires-Python: >=3.10
License-File: LICENSE
Requires-Dist: tabulate
Requires-Dist: tomli; python_version < "3.11"
Provides-Extra: build
Requires-Dist: build; extra == "build"
Requires-Dist: twine; extra == "build"
Provides-Extra: dev
Requires-Dist: bump2version; extra == "dev"
Requires-Dist: pytest; extra == "dev"
Dynamic: license-file
